pretix_swap/__init__.py
pretix_swap/forms.py
pretix_swap/models.py
pretix_swap/signals.py
pretix_swap/urls.py
pretix_swap/utils.py
pretix_swap/views.py
pretix_swap/locale/django.pot
pretix_swap/locale/de/LC_MESSAGES/django.mo
pretix_swap/locale/de/LC_MESSAGES/django.po
pretix_swap/locale/de_Informal/.gitkeep
pretix_swap/locale/de_Informal/LC_MESSAGES/django.mo
pretix_swap/locale/de_Informal/LC_MESSAGES/django.po
pretix_swap/migrations/0001_initial.py
pretix_swap/migrations/0002_restructure_swap_groups.py
pretix_swap/migrations/0003_auto_20210616_2249.py
pretix_swap/migrations/__init__.py
pretix_swap/static/pretix_swap/.gitkeep
pretix_swap/static/pretix_swap/order.js
pretix_swap/static/pretix_swap/settings.js
pretix_swap/static/pretix_swap/swap.js
pretix_swap/templates/pretix_swap/.gitkeep
pretix_swap/templates/pretix_swap/fragment_swap_settings.html
pretix_swap/templates/pretix_swap/control/create.html
pretix_swap/templates/pretix_swap/control/delete.html
pretix_swap/templates/pretix_swap/control/edit.html
pretix_swap/templates/pretix_swap/control/settings.html
pretix_swap/templates/pretix_swap/control/stats.html
pretix_swap/templates/pretix_swap/presale/cancel.html
pretix_swap/templates/pretix_swap/presale/new.html
pretix_swap/templates/pretix_swap/presale/new_confirm.html
pretix_swap/templates/pretix_swap/presale/new_details.html
pretix_swap/templates/pretix_swap/presale/new_position.html
pretix_swap/templates/pretix_swap/presale/new_refund.html
pretix_swap/templates/pretix_swap/presale/new_type.html
pretix_swap/templates/pretix_swap/presale/order_box.html
pretix_swap/templates/pretix_swap/presale/require_approval_box.html
pretix_swap-0.4.0.dist-info/licenses/LICENSE
pretix_swap-0.4.0.dist-info/METADATA
pretix_swap-0.4.0.dist-info/WHEEL
pretix_swap-0.4.0.dist-info/entry_points.txt
pretix_swap-0.4.0.dist-info/top_level.txt
pretix_swap-0.4.0.dist-info/RECORD
