Metadata-Version: 2.4
Name: pretix-swap
Version: 0.4.0
Summary: Swap tickets, anonymously or with specific other attendees. Also supports canceling tickets if (and only if) another ticket is purchased.
Author-email: Tobias Kunze <r@rixx.de>
Maintainer-email: Tobias Kunze <r@rixx.de>
License: Apache
Project-URL: homepage, https://github.com/rixx/pretix-swap
Project-URL: repository, https://github.com/rixx/pretix-swap
Keywords: pretix
License-File: LICENSE
Dynamic: license-file
